sqlalchemy_i18n/__init__.py
sqlalchemy_i18n/builders.py
sqlalchemy_i18n/comparators.py
sqlalchemy_i18n/exc.py
sqlalchemy_i18n/expressions.py
sqlalchemy_i18n/manager.py
sqlalchemy_i18n/translatable.py
sqlalchemy_i18n/utils.py
SQLAlchemy_i18n-1.1.0.dist-info/LICENSE
SQLAlchemy_i18n-1.1.0.dist-info/METADATA
SQLAlchemy_i18n-1.1.0.dist-info/WHEEL
SQLAlchemy_i18n-1.1.0.dist-info/top_level.txt
SQLAlchemy_i18n-1.1.0.dist-info/RECORD
