Metadata-Version: 2.1
Name: SQLAlchemy-i18n
Version: 1.1.0
Summary: Internationalization extension for SQLAlchemy models.
Home-page: https://github.com/kvesteri/sqlalchemy-i18n
Author: Konsta Vesterinen
Author-email: konsta@fastmonkeys.com
License: BSD
Platform: any
Classifier: Environment :: Web Environment
Classifier: Intended Audience :: Developers
Classifier: License :: OSI Approved :: BSD License
Classifier: Operating System :: OS Independent
Classifier: Programming Language :: Python
Classifier: Programming Language :: Python :: 3
Classifier: Programming Language :: Python :: 3.6
Classifier: Programming Language :: Python :: 3.7
Classifier: Programming Language :: Python :: 3.8
Classifier: Topic :: Internet :: WWW/HTTP :: Dynamic Content
Classifier: Topic :: Software Development :: Libraries :: Python Modules
Requires-Python: >=3.6
Provides-Extra: test
